[
    {
        "author": "Aleksandra Jachtoma",
        "title": "Composition, 1989",
        "medium": "oil/canvas",
        "dimensions": "100 x 81 cm",
        "hammer_price": "32,000 PLN"
    },
    {
        "author": "Janusz Eysymont",
        "title": "Composition, 1990",
        "medium": "oil/canvas",
        "dimensions": "116 x 81 cm",
        "hammer_price": "18,000 PLN"
    },
    {
        "author": "Jan Tarasin",
        "title": "\"Situation III\", 1997",
        "medium": "oil/canvas",
        "dimensions": "68 x 98 cm",
        "hammer_price": "220,000 PLN"
    },
    {
        "author": "Julian Stanczak",
        "title": "\"Concurrence\", 1963",
        "medium": "acrylic/canvas",
        "dimensions": "95 x 95 cm",
        "hammer_price": "220,000 PLN"
    },
    {
        "author": "Victor Vasarely",
        "title": "\"Bikub\", 1972",
        "medium": "acrylic/canvas",
        "dimensions": "151 x 75 cm",
        "hammer_price": "580,000 PLN"
    },
    {
        "author": "Victor Vasarely",
        "title": "\"Kita\", 1970",
        "medium": "acrylic/canvas",
        "dimensions": "81 x 81 cm",
        "hammer_price": "380,000 PLN"
    },
    {
        "author": "Ryszard Winiarski",
        "title": "\"Penetration of real space\", 1974",
        "medium": "acrylic, relief/board",
        "dimensions": "50 x 50 cm",
        "hammer_price": "210,000 PLN"
    },
    {
        "author": "Andrzej Nowacki",
        "title": "\"20.11.15\", 2015",
        "medium": "acrylic, relief/plywood",
        "dimensions": "99 x 99 cm",
        "hammer_price": "80,000 PLN"
    },
    {
        "author": "Jan Dobkowski",
        "title": "\"XIX\" fromt the series \"Magical paintings\", 1975/2020",
        "medium": "acrylic/canvas",
        "dimensions": "54 x 54 cm",
        "hammer_price": "38,000 PLN"
    },
    {
        "author": "Jan Dobkowski",
        "title": "\"Possessive woman\", 1971",
        "medium": "oil/canvas",
        "dimensions": "41 x 33 cm",
        "hammer_price": "55,000 PLN"
    },
    {
        "author": "Jerzy Nowosielski",
        "title": "Cityscape (Krakow), 1973",
        "medium": "oil/canvas",
        "dimensions": "60 x 75 cm",
        "hammer_price": "240,000 PLN"
    },
    {
        "author": "Jerzy Kujawski",
        "title": "Untitled, 1960",
        "medium": "oil/canvas",
        "dimensions": "33 x 65 cm",
        "hammer_price": "14,000 PLN"
    },
    {
        "author": "Jan Lebenstein",
        "title": "\"Figura no 173\", 1962",
        "medium": "oil/canvas",
        "dimensions": "128.9 x 96.5 cm",
        "hammer_price": "220,000 PLN"
    },
    {
        "author": "Aleksander Roszkowski",
        "title": "\"Bright\", 2016",
        "medium": "oil/canvas",
        "dimensions": "190 x 190 cm",
        "hammer_price": "26,000 PLN"
    },
    {
        "author": "Danuta Lewandowska",
        "title": "Composition 31/75, 1975",
        "medium": "acrylic, relief/canvas",
        "dimensions": "53 x 49 cm",
        "hammer_price": "17,000 PLN"
    },
    {
        "author": "Jozef Robakowski",
        "title": "From the cycle 'Energetic Angles', 1975/2003",
        "medium": "acrylic/canvas",
        "dimensions": "70 x 70 cm",
        "hammer_price": "18,000 PLN"
    },
    {
        "author": "Koji Kamoji",
        "title": "Untitled, 1993",
        "medium": "assemblage, mixed media/plate",
        "dimensions": "20 x 20 cm",
        "hammer_price": "6,000 PLN"
    },
    {
        "author": "Jerzy Duda-Gracz",
        "title": "Composition, 1992",
        "medium": "oil/canvas",
        "dimensions": "61 x 50 cm",
        "hammer_price": "65,000 PLN"
    },
    {
        "author": "Teofil Ociepka",
        "title": "Dragon, 1954",
        "medium": "oil/paperboard",
        "dimensions": "21.7 x 30.5 cm (dimensions in passe-partout window)",
        "hammer_price": "40,000 PLN"
    },
    {
        "author": "Bronislaw Kierzkowski",
        "title": "\"Factural composition no 449\", 1959",
        "medium": "mixed media, relief/board",
        "dimensions": "49 x 47 cm",
        "hammer_price": "30,000 PLN"
    },
    {
        "author": "Erna Rosenstein",
        "title": "\"Silence is burning\", 1995",
        "medium": "oil/canvas",
        "dimensions": "56 x 56 cm",
        "hammer_price": "48,000 PLN"
    },
    {
        "author": "Henryk Musialowicz",
        "title": "From the series \"Reminiscencje\", 1978",
        "medium": "oil/board",
        "dimensions": "62 x 48 cm",
        "hammer_price": "14,000 PLN"
    },
    {
        "author": "Jadwiga Maziarska",
        "title": "\"No 6\", 1976",
        "medium": "oil, acrylic/canvas",
        "dimensions": "75 x 54 cm",
        "hammer_price": "42,000 PLN"
    },
    {
        "author": "Jozef Szajna",
        "title": "\"Ashes\", 1990",
        "medium": "oil/canvas",
        "dimensions": "90 x 120 cm",
        "hammer_price": "11,000 PLN"
    },
    {
        "author": "Andrzej S. Kowalski",
        "title": "\"Painting R-p-f \", 1970",
        "medium": "oil/canvas",
        "dimensions": "100 x 70 cm",
        "hammer_price": "19,000 PLN"
    },
    {
        "author": "Jozef Jarema",
        "title": "Composition, 1959",
        "medium": "oil/canvas",
        "dimensions": "89 x 139 cm",
        "hammer_price": "28,000 PLN"
    },
    {
        "author": "Wlodzimierz Pawlak",
        "title": "\"Note about art 4/V\", 2016",
        "medium": "oil/canvas",
        "dimensions": "33 x 24 cm",
        "hammer_price": "12,000 PLN"
    },
    {
        "author": "Tadeusz Dominik",
        "title": "\"Winter\" from the series \"Four Seasons\", 1993",
        "medium": "oil/canvas",
        "dimensions": "81 x 101 cm",
        "hammer_price": "50,000 PLN"
    },
    {
        "author": "Edward Dwurnik",
        "title": "\"Don't shoot yet!\" from the \"Sportsmen series\", 1986-1997",
        "medium": "oil/canvas",
        "dimensions": "146 x 114 cm",
        "hammer_price": "90,000 PLN"
    },
    {
        "author": "Slawomir Lewczuk",
        "title": "\"Grass II\"",
        "medium": "oil, acrylic/canvas",
        "dimensions": "99 x 79 cm",
        "hammer_price": "7,000 PLN"
    }
]